aiub_notes_dl/__init__.py
aiub_notes_dl-1.0.0.post2.dist-info/entry_points.txt
aiub_notes_dl-1.0.0.post2.dist-info/LICENSE
aiub_notes_dl-1.0.0.post2.dist-info/WHEEL
aiub_notes_dl-1.0.0.post2.dist-info/METADATA
aiub_notes_dl-1.0.0.post2.dist-info/RECORD
